taskx/__init__.py
taskx/cli/__init__.py
taskx/cli/main.py
taskx/cli/commands/__init__.py
taskx/cli/commands/completion.py
taskx/cli/commands/graph.py
taskx/cli/commands/watch.py
taskx/completion/__init__.py
taskx/completion/base.py
taskx/completion/bash.py
taskx/completion/fish.py
taskx/completion/powershell.py
taskx/completion/zsh.py
taskx/core/__init__.py
taskx/core/config.py
taskx/core/dependency.py
taskx/core/env.py
taskx/core/hooks.py
taskx/core/prompts.py
taskx/core/runner.py
taskx/core/task.py
taskx/execution/__init__.py
taskx/execution/parallel.py
taskx/execution/watcher.py
taskx/formatters/__init__.py
taskx/formatters/console.py
taskx/templates/__init__.py
taskx/templates/base.py
taskx/templates/data_science/template.py
taskx/templates/django/template.py
taskx/templates/fastapi/template.py
taskx/templates/python_library/template.py
taskx/utils/__init__.py
taskx/utils/platform.py
taskx/utils/secure_exec.py
taskx/utils/shell.py
taskx/utils/validation.py
taskx-0.2.1.dist-info/METADATA
taskx-0.2.1.dist-info/WHEEL
taskx-0.2.1.dist-info/entry_points.txt
taskx-0.2.1.dist-info/licenses/LICENSE
taskx-0.2.1.dist-info/RECORD
