Metadata-Version: 2.4
Name: taskx
Version: 0.2.1
Summary: Modern Python task runner - npm scripts for Python
Project-URL: Homepage, https://github.com/0xV8/taskx
Project-URL: Repository, https://github.com/0xV8/taskx
Project-URL: Bug Tracker, https://github.com/0xV8/taskx/issues
Author: taskx Project
License: Proprietary - See LICENSE file
License-File: LICENSE
Keywords: automation,build tool,cli,make,npm scripts,python,task runner,workflow
Classifier: Development Status :: 3 - Alpha
Classifier: Environment :: Console
Classifier: Intended Audience :: Developers
Classifier: License :: Other/Proprietary License
Classifier: Programming Language :: Python :: 3
Classifier: Programming Language :: Python :: 3.8
Classifier: Programming Language :: Python :: 3.9
Classifier: Programming Language :: Python :: 3.10
Classifier: Programming Language :: Python :: 3.11
Classifier: Programming Language :: Python :: 3.12
Classifier: Topic :: Software Development :: Build Tools
Classifier: Topic :: System :: Systems Administration
Requires-Python: >=3.8
Requires-Dist: click>=8.0.0
Requires-Dist: jinja2>=3.1.0
Requires-Dist: python-dotenv>=1.0.0
Requires-Dist: questionary>=2.0.0
Requires-Dist: rich>=13.0.0
Requires-Dist: tomli>=2.0.0; python_version < '3.11'
Requires-Dist: watchfiles>=0.18.0
Provides-Extra: dev
Requires-Dist: black>=23.0.0; extra == 'dev'
Requires-Dist: isort>=5.12.0; extra == 'dev'
Requires-Dist: memory-profiler>=0.61.0; extra == 'dev'
Requires-Dist: mypy>=1.0.0; extra == 'dev'
Requires-Dist: pre-commit>=3.0.0; extra == 'dev'
Requires-Dist: pytest-asyncio>=0.21.0; extra == 'dev'
Requires-Dist: pytest-benchmark>=4.0.0; extra == 'dev'
Requires-Dist: pytest-cov>=4.0.0; extra == 'dev'
Requires-Dist: pytest-mock>=3.11.0; extra == 'dev'
Requires-Dist: pytest-timeout>=2.1.0; extra == 'dev'
Requires-Dist: pytest-xdist>=3.3.0; extra == 'dev'
Requires-Dist: pytest>=7.0.0; extra == 'dev'
Requires-Dist: ruff>=0.1.0; extra == 'dev'
Requires-Dist: tox>=4.0.0; extra == 'dev'
Requires-Dist: types-setuptools; extra == 'dev'
